app/config.pyi
app/env.pyi
app/py.typed
app/app/codemod/compilation/models/github_named_user_context.pyi
app/app/codemod/compilation/models/pr_part_context.pyi
app/app/codemod/compilation/models/pull_request_context.pyi
app/codemod/compilation/models/context.pyi
app/codemod/compilation/models/github_named_user_context.pyi
app/codemod/compilation/models/pr_options.pyi
app/codemod/compilation/models/pr_part_context.pyi
app/codemod/compilation/models/pull_request_context.pyi
app/modal_app/studio/prompts/git_utils.pyi
app/monitoring/logging/logger.pyi
app/utils/trace.pyi
app/utils/aws/credentials.pyi
app/utils/codemod/codemod_writer_decorators.pyi
app/utils/sentry/relay.pyi
codegen_types-0.275.0.dist-info/METADATA
codegen_types-0.275.0.dist-info/WHEEL
codegen_types-0.275.0.dist-info/RECORD
